nrgmodbus/__init__.py
nrgmodbus/dbhandler.py
nrgmodbus/utilities.py
nrgmodbus/ipackaccess/__init__.py
nrgmodbus/ipackaccess/_registers.py
nrgmodbus/ipackaccess/ipackaccess.py
nrgmodbus/ipackaccess/registers.py
nrgmodbus/spidar/__init__.py
nrgmodbus/spidar/registers.py
nrgmodbus/spidar/spidar.py
nrgmodbus-0.3.0.dist-info/LICENSE
nrgmodbus-0.3.0.dist-info/METADATA
nrgmodbus-0.3.0.dist-info/WHEEL
nrgmodbus-0.3.0.dist-info/top_level.txt
nrgmodbus-0.3.0.dist-info/zip-safe
nrgmodbus-0.3.0.dist-info/RECORD
