Metadata-Version: 2.1
Name: nrgmodbus
Version: 0.3.0
Summary: library for making modbus connections to NRG Systems devices.
Home-page: https://github.com/nrgpy/nrgmodbus
Author: NRG Systems, Inc.
Author-email: support@nrgsystems.com
License: MIT
Keywords: nrg systems symphoniepro ipackaccess wind modbus spidar
Platform: UNKNOWN
Requires-Python: >=3.0
Requires-Dist: pymodbus
Requires-Dist: requests
